Metadata-Version: 2.1
Name: ch09-ep01-lista
Version: 1.0
Summary: Módulo para controle de listas
Home-page: http://www.altabooks.com.br
Author: Marcelo Ribeiro
Author-email: celopr@hotmail.com
License: UNKNOWN
Platform: UNKNOWN
